prompters/__init__.py
prompters-0.1.0.dist-info/METADATA
prompters-0.1.0.dist-info/WHEEL
prompters-0.1.0.dist-info/RECORD
