Metadata-Version: 2.3
Name: prompters
Version: 0.1.0
Summary: Add your description here
Author-email: Hicham Randrianarivo <hicham.randrianarivo@gmail.com>
Requires-Python: >=3.8
Requires-Dist: absl-py>=2.1.0
Requires-Dist: attrs>=23.2.0
Requires-Dist: beartype>=0.18.5
Requires-Dist: jinja2>=3.1.4
Requires-Dist: plum-dispatch>=2.3.5
Requires-Dist: ruff>=0.4.4
